odoo/addons/l10n_cl_sii_folio/README.rst
odoo/addons/l10n_cl_sii_folio/__init__.py
odoo/addons/l10n_cl_sii_folio/__manifest__.py
odoo/addons/l10n_cl_sii_folio/i18n/es_CL.po
odoo/addons/l10n_cl_sii_folio/i18n/l10n_cl_sii_folio.pot
odoo/addons/l10n_cl_sii_folio/models/__init__.py
odoo/addons/l10n_cl_sii_folio/models/account_journal.py
odoo/addons/l10n_cl_sii_folio/models/account_journal_document.py
odoo/addons/l10n_cl_sii_folio/models/account_move.py
odoo/addons/l10n_cl_sii_folio/models/ir_sequence.py
odoo/addons/l10n_cl_sii_folio/models/ir_sequence_folio.py
odoo/addons/l10n_cl_sii_folio/readme/CONTRIBUTORS.rst
odoo/addons/l10n_cl_sii_folio/readme/DESCRIPTION.rst
odoo/addons/l10n_cl_sii_folio/readme/USAGE.rst
odoo/addons/l10n_cl_sii_folio/security/ir.model.access.csv
odoo/addons/l10n_cl_sii_folio/static/description/icon.png
odoo/addons/l10n_cl_sii_folio/static/description/index.html
odoo/addons/l10n_cl_sii_folio/views/account_journal.xml
odoo/addons/l10n_cl_sii_folio/views/account_journal_document.xml
odoo/addons/l10n_cl_sii_folio/views/ir_sequence.xml
odoo/addons/l10n_cl_sii_folio/views/ir_sequence_folio.xml
odoo12_addon_l10n_cl_sii_folio-12.0.1.2.0.dist-info/METADATA
odoo12_addon_l10n_cl_sii_folio-12.0.1.2.0.dist-info/WHEEL
odoo12_addon_l10n_cl_sii_folio-12.0.1.2.0.dist-info/top_level.txt
odoo12_addon_l10n_cl_sii_folio-12.0.1.2.0.dist-info/RECORD
